[
  {
    "id": "jajecznica",
    "name": "Jajecznica",
    "description": "Pyszna. Na jachcie może być konieczność robienia na 2 tury.",
    "mealType": [
      "śniadanie",
      "kolacja"
    ],
    "difficulty": 3,
    "ingredients": [
      {
        "id": "jajka",
        "amount": 3
      },
      {
        "id": "sol",
        "amount": 1
      },
      {
        "id": "pieprz",
        "amount": 1
      },
      {
        "id": "chleb",
        "amount": 0.15
      },
      {
        "id": "maslo",
        "amount": 2
      }
    ],
    "instructions": [
      "Każdy umie zrobić jajecznicę."
    ],
    "developedBy": "Przemysław Onak"
  },
  {
    "id": "pesto-z-tuczykiem",
    "name": "Pesto z tuńczykiem",
    "description": "Szybkie i dobre, łatwo zrobić nawet na fali. Zamiast zielonego pesto można użyć czerwonego.",
    "mealType": [
      "obiad"
    ],
    "difficulty": 2,
    "ingredients": [
      {
        "id": "tunczyk_w_sosie_wlasnym",
        "amount": 75
      },
      {
        "id": "makaron_penne",
        "amount": 90
      },
      {
        "id": "pesto",
        "amount": 40
      }
    ],
    "instructions": [
      "Gotujemy i cedzimy makaron",
      "Dodajemy tuńczyka i pesto, mieszkamy"
    ],
    "developedBy": "Przemysław Onak"
  },
  {
    "id": "pesto-z-tuczykiem-i-parmezanem",
    "name": "Pesto z tuńczykiem i parmezanem",
    "description": "Szybkie i dobre, łatwo zrobić nawet na fali. Zamiast zielonego pesto można użyć czerwonego. Zamiast Parmezanu można użyć Grana Padano lub innego startego sera.",
    "mealType": [
      "obiad"
    ],
    "difficulty": 2,
    "ingredients": [
      {
        "id": "tunczyk_w_sosie_wlasnym",
        "amount": 75
      },
      {
        "id": "makaron_penne",
        "amount": 90
      },
      {
        "id": "pesto",
        "amount": 40
      },
      {
        "id": "parmezan",
        "amount": 15
      }
    ],
    "instructions": [
      "Gotujemy i cedzimy makaron",
      "Dodajemy tuńczyka i pesto, mieszkamy",
      "Przed podaniem posypać parmezanem"
    ],
    "developedBy": "Przemysław Onak"
  }
]